{
  "activeState": null,
  "attributes": {},
  "baseStyles": {
    "position": "relative"
  },
  "blockId": "859u6md8y",
  "blockName": "app logo",
  "children": [
    "v45i6chxy"
  ],
  "classes": [],
  "customAttributes": {},
  "dataKey": null,
  "dynamicValues": [],
  "element": null,
  "extendedFromComponent": null,
  "innerHTML": null,
  "isChildOfComponent": "5yb01f65yb01f65y",
  "isRepeaterBlock": false,
  "mobileStyles": {},
  "originalElement": "",
  "props": {},
  "rawStyles": {},
  "referenceBlockId": "v01j7tpza",
  "tabletStyles": {},
  "visibilityCondition": null
}