{
  "activeState": null,
  "attributes": {},
  "baseStyles": {},
  "blockId": "kgkjf8o06",
  "blockName": "wrapper",
  "children": [
    "54ab4iexa",
    "ho6r10a51"
  ],
  "classes": [],
  "customAttributes": {},
  "dataKey": null,
  "dynamicValues": [],
  "element": null,
  "extendedFromComponent": null,
  "innerHTML": null,
  "isChildOfComponent": "1sxw12i1sxw12i1s",
  "isRepeaterBlock": false,
  "mobileStyles": {},
  "originalElement": "",
  "props": {},
  "rawStyles": {},
  "referenceBlockId": "qt53kedan",
  "tabletStyles": {},
  "visibilityCondition": null
}