{
  "activeState": null,
  "attributes": {},
  "baseStyles": {},
  "blockId": "73bsmnglu",
  "blockName": "container",
  "children": [
    "z2kmon0rb",
    "madxijpsx"
  ],
  "classes": [],
  "customAttributes": {},
  "dataKey": null,
  "dynamicValues": [],
  "element": null,
  "extendedFromComponent": null,
  "innerHTML": null,
  "isChildOfComponent": "76776y376776y376",
  "isRepeaterBlock": false,
  "mobileStyles": {},
  "originalElement": null,
  "props": {},
  "rawStyles": {},
  "referenceBlockId": "3gbollfft",
  "tabletStyles": {},
  "visibilityCondition": null
}