{
  "activeState": null,
  "attributes": {},
  "baseStyles": {},
  "blockId": "3jfh8tn1r",
  "blockName": "State",
  "children": [],
  "classes": [],
  "customAttributes": {},
  "dataKey": null,
  "dynamicValues": [],
  "element": null,
  "extendedFromComponent": null,
  "innerHTML": null,
  "isChildOfComponent": "1sxw12i1sxw12i1s",
  "isRepeaterBlock": false,
  "mobileStyles": {},
  "originalElement": "",
  "props": {},
  "rawStyles": {},
  "referenceBlockId": "c5o8ov5eg",
  "tabletStyles": {},
  "visibilityCondition": null
}