{
  "activeState": null,
  "attributes": {},
  "baseStyles": {},
  "blockId": "omvrrd9pz",
  "blockName": "Apparel",
  "children": [],
  "classes": [],
  "customAttributes": {},
  "dataKey": null,
  "dynamicValues": [],
  "element": null,
  "extendedFromComponent": null,
  "innerHTML": null,
  "isChildOfComponent": "ube0tcube0tcube0",
  "isRepeaterBlock": false,
  "mobileStyles": {},
  "originalElement": "",
  "props": {},
  "rawStyles": {},
  "referenceBlockId": "q9vl9h7ot",
  "tabletStyles": {},
  "visibilityCondition": null
}